MANIFEST.in
README.rst
setup.cfg
setup.py
pymus/__init__.py
pymus/tools.py
pymus.egg-info/PKG-INFO
pymus.egg-info/SOURCES.txt
pymus.egg-info/dependency_links.txt
pymus.egg-info/not-zip-safe
pymus.egg-info/top_level.txt
pymus/convert/__init__.py
pymus/convert/converter.py
pymus/features/__init__.py
pymus/features/f0_contour_features.py
pymus/sisa/__init__.py
pymus/sisa/main.py
pymus/sisa/f0_tracking/__init__.py
pymus/sisa/f0_tracking/estimator.py
pymus/sisa/f0_tracking/f0_tracking_peak_tracking.py
pymus/sisa/f0_tracking/f0_tracking_pyin.py
pymus/sisa/loudness/__init__.py
pymus/sisa/loudness/estimator.py
pymus/sisa/loudness/loudness_critical_band_approximation.py
pymus/sisa/tuning/__init__.py
pymus/sisa/tuning/estimator.py
pymus/sisa/tuning/tuning_nnls_chroma.py
pymus/test/__init__.py
pymus/test/test_converter.py
pymus/test/test_features.py
pymus/test/test_sisa.py
pymus/test/test_transformer.py
pymus/test/data/__init__.py
pymus/test/data/duration.txt
pymus/test/data/loudness.txt
pymus/test/data/loudness_median.txt
pymus/test/data/loudness_rel_peak_pos.txt
pymus/test/data/loudness_std.txt
pymus/test/data/loudness_temp_centroid.txt
pymus/test/data/onset.txt
pymus/test/data/pitch.txt
pymus/test/data/test_reass_spec_NFFT.txt
pymus/test/data/test_reass_spec_blocksize.txt
pymus/test/data/test_reass_spec_f.txt
pymus/test/data/test_reass_spec_fs.txt
pymus/test/data/test_reass_spec_hopsize.txt
pymus/test/data/test_reass_spec_if.txt
pymus/test/data/test_reass_spec_spec.txt
pymus/test/data/test_reass_spec_x.txt
pymus/test/data/test_sisa.wav
pymus/test/data/test_stft_NFFT.txt
pymus/test/data/test_stft_blocksize.txt
pymus/test/data/test_stft_hopsize.txt
pymus/test/data/test_stft_spec_imag.txt
pymus/test/data/test_stft_spec_real.txt
pymus/test/data/test_stft_x.txt
pymus/test/data/test_transform.wav
pymus/test/data/tuning_freq.txt
pymus/transform/__init__.py
pymus/transform/transformer.py
pymus/wrapper/__init__.py
pymus/wrapper/sonic_visualiser.py