Metadata-Version: 1.0
Name: pymus
Version: 0.2.5
Summary: Tools for audio analysis, special focus on score-informed audio analysis of instrumental / vocal solo recordings
Home-page: UNKNOWN
Author: Jakob Abesser
Author-email: nudelsalat@posteo.de
License: MIT
Keywords: score-informed audio analysis solo recordings tuning loudness intonation music information retrieval
Platform: UNKNOWN
